Metadata-Version: 2.1
Name: vialink-utils-module
Version: 1.0.1
Summary: Vialink Utils
Home-page: 
Author: yurananatul.m
Author-email: yurananatul.m@via.link
License: Apache 2.0
Requires-Python: >=3.7
